lndgrpc/__init__.py
lndgrpc/client.py
lndgrpc/common.py
lndgrpc/errors.py
lndgrpc/rpc_pb2.py
lndgrpc/rpc_pb2_grpc.py
lndgrpc/aio/__init__.py
lndgrpc/aio/async_client.py
lndgrpc/async/__init__.py
lndgrpc/async/async_client.py
lndgrpc-0.2.0.dist-info/LICENSE
lndgrpc-0.2.0.dist-info/METADATA
lndgrpc-0.2.0.dist-info/WHEEL
lndgrpc-0.2.0.dist-info/top_level.txt
lndgrpc-0.2.0.dist-info/RECORD
