Metadata-Version: 2.1
Name: lndgrpc
Version: 0.2.0
Summary: An rpc client for LND (lightning network deamon)
Home-page: https://github.com/adrienemery/lnd-grpc-client
Author: Adrien Emery
Author-email: adrien.emery@gmail.com
License: MIT
Download-URL: https://github.com/adrienemery/lnd-grpc-client/archive/0.2.0.tar.gz
Keywords: lnd,lightning-network,bitcoin,grpc,rpc,async
Platform: UNKNOWN
Classifier: Development Status :: 3 - Alpha
Classifier: License :: OSI Approved :: MIT License
Classifier: Programming Language :: Python :: 2.7
Classifier: Programming Language :: Python :: 3.4
Classifier: Programming Language :: Python :: 3.5
Classifier: Programming Language :: Python :: 3.6
Classifier: Programming Language :: Python :: 3.7
Requires-Python: >=2.7, !=3.0.*, !=3.1.*, !=3.2.*, !=3.3.*, <4
Requires-Dist: grpcio
Requires-Dist: grpcio-tools
Requires-Dist: googleapis-common-protos
Requires-Dist: aiogrpc
